trac_rpc/__about__.py
trac_rpc/__init__.py
trac_rpc/client.py
trac_rpc/exceptions.py
trac_rpc/models.py
trac_rpc/validators.py
trac_rpc-0.1.3.dist-info/METADATA
trac_rpc-0.1.3.dist-info/WHEEL
trac_rpc-0.1.3.dist-info/licenses/LICENSE
trac_rpc-0.1.3.dist-info/RECORD
