Metadata-Version: 2.4
Name: trac-rpc
Version: 0.1.3
Summary: Modern, Pythonic and type-safe Trac RPC API client
Author-email: "Yury V. Zaytsev" <yury@shurup.com>
License-Expression: MIT
License-File: LICENSE
Keywords: api,httpx,pydantic,rpc,trac
Classifier: Development Status :: 4 - Beta
Classifier: Intended Audience :: Developers
Classifier: License :: OSI Approved :: MIT License
Classifier: Programming Language :: Python :: 3
Classifier: Programming Language :: Python :: 3 :: Only
Classifier: Programming Language :: Python :: 3.12
Classifier: Programming Language :: Python :: 3.13
Classifier: Topic :: Software Development :: Libraries :: Python Modules
Requires-Python: >=3.12
Requires-Dist: httpx
Requires-Dist: pydantic>=2.0
